home/raymond/catkin_ws/src/topic_store/src/CHANGELOG.rst
home/raymond/catkin_ws/src/topic_store/src/LICENCE
home/raymond/catkin_ws/src/topic_store/src/README.md
home/raymond/catkin_ws/src/topic_store/src/extra_requirements.txt
home/raymond/catkin_ws/src/topic_store/src/package.xml
home/raymond/catkin_ws/src/topic_store/src/requirements.txt
topic_store/__init__.py
topic_store/api.py
topic_store/convert.py
topic_store/data.py
topic_store/database.py
topic_store/file_parsers.py
topic_store/filesystem.py
topic_store/load_balancer.py
topic_store/sanitation.py
topic_store/scenario.py
topic_store/store.py
topic_store/utils.py
topic_store/msg/_CollectDataAction.py
topic_store/msg/_CollectDataActionFeedback.py
topic_store/msg/_CollectDataActionGoal.py
topic_store/msg/_CollectDataActionResult.py
topic_store/msg/_CollectDataFeedback.py
topic_store/msg/_CollectDataGoal.py
topic_store/msg/_CollectDataResult.py
topic_store/msg/__init__.py
topic_store-0.1.8.dist-info/LICENCE
topic_store-0.1.8.dist-info/METADATA
topic_store-0.1.8.dist-info/WHEEL
topic_store-0.1.8.dist-info/dependency_links.txt
topic_store-0.1.8.dist-info/entry_points.txt
topic_store-0.1.8.dist-info/top_level.txt
topic_store-0.1.8.dist-info/RECORD
