Metadata-Version: 2.1
Name: topic-store
Version: 0.1.8
Summary: ROS package used for serialising common ROS messages to a database or filesystem.
Home-page: https://github.com/RaymondKirk/topic_store
Author: Raymond Tunstill
Author-email: ray.tunstill@live.co.uk
License: MIT
Platform: UNKNOWN
Classifier: Programming Language :: Python :: 2
Classifier: Programming Language :: Python :: 3
Requires-Python: >=2.7
Requires-Dist: numpy (>=1.13.3)
Requires-Dist: pathlib (>=1.0.1)
Requires-Dist: pymongo (>=3.6.1)
Requires-Dist: pyyaml (>=3.12)
Requires-Dist: rospkg (>=1.2.6)
Requires-Dist: tqdm (>=4.19.0)
Requires-Dist: actionlib
Requires-Dist: actionlib-msgs
Requires-Dist: geometry-msgs
Requires-Dist: sensor-msgs
Requires-Dist: nav-msgs
Requires-Dist: ros-numpy
Requires-Dist: genpy (<=2000,>=0.6.14)
Requires-Dist: pathlib
Requires-Dist: tqdm
Requires-Dist: rosbag
Requires-Dist: roslib
Requires-Dist: rospy
